aep_otel/__init__.py
aep_otel/hooks.py
aep_otel/tracing.py
aep_otel-1.1.4.dist-info/METADATA
aep_otel-1.1.4.dist-info/WHEEL
aep_otel-1.1.4.dist-info/RECORD
